django_auth_ldap/__init__.py
django_auth_ldap/backend.py
django_auth_ldap/config.py
django_auth_ldap/version.py
django_auth_ldap_custom-2.4.1.dist-info/LICENSE
django_auth_ldap_custom-2.4.1.dist-info/METADATA
django_auth_ldap_custom-2.4.1.dist-info/WHEEL
django_auth_ldap_custom-2.4.1.dist-info/top_level.txt
django_auth_ldap_custom-2.4.1.dist-info/RECORD
