Metadata-Version: 2.1
Name: django-auth-ldap-custom
Version: 2.4.1
Summary: Django LDAP authentication backend.
Home-page: https://github.com/django-auth-ldap/django-auth-ldap
Author: Peter Sagerson
Author-email: psagers@ignorare.net
License: BSD
Project-URL: Documentation, https://django-auth-ldap.readthedocs.io/
Project-URL: Source, https://github.com/django-auth-ldap/django-auth-ldap
Project-URL: Tracker, https://github.com/django-auth-ldap/django-auth-ldap/issues
Platform: UNKNOWN
Classifier: Development Status :: 5 - Production/Stable
Classifier: Environment :: Web Environment
Classifier: Framework :: Django
Classifier: Framework :: Django :: 2.2
Classifier: Framework :: Django :: 3.0
Classifier: Framework :: Django :: 3.1
Classifier: Framework :: Django :: 3.2
Classifier: Intended Audience :: Developers
Classifier: Intended Audience :: System Administrators
Classifier: License :: OSI Approved :: BSD License
Classifier: Programming Language :: Python
Classifier: Programming Language :: Python :: 3
Classifier: Programming Language :: Python :: 3 :: Only
Classifier: Programming Language :: Python :: 3.6
Classifier: Programming Language :: Python :: 3.7
Classifier: Programming Language :: Python :: 3.8
Classifier: Programming Language :: Python :: 3.9
Classifier: Topic :: Internet :: WWW/HTTP
Classifier: Topic :: Software Development :: Libraries :: Python Modules
Classifier: Topic :: System :: Systems Administration :: Authentication/Directory :: LDAP
Requires-Python: >=3.6
License-File: LICENSE
Requires-Dist: Django (>=2.2)
Requires-Dist: python-ldap (>=3.1)
